README.rst
setup.py
mackinac/SeedClient.py
mackinac/__init__.py
mackinac/genome.py
mackinac/likelihood.py
mackinac/modelseed.py
mackinac/workspace.py
mackinac.egg-info/PKG-INFO
mackinac.egg-info/SOURCES.txt
mackinac.egg-info/dependency_links.txt
mackinac.egg-info/requires.txt
mackinac.egg-info/top_level.txt
mackinac/test/__init__.py
mackinac/test/conftest.py
mackinac/test/test_genome.py
mackinac/test/test_modelseed.py
mackinac/test/test_workspace.py